bramin/__init__.py
bramin/_utils.py
bramin/curry.py
bramin/io.py
bramin/patch.py
bramin/pipe.py
bramin/subp.py
bramin-0.0.1.dist-info/LICENSE
bramin-0.0.1.dist-info/METADATA
bramin-0.0.1.dist-info/WHEEL
bramin-0.0.1.dist-info/top_level.txt
bramin-0.0.1.dist-info/RECORD
